wavemap/__init__.py
wavemap/convert.py
wavemap/docs.py
wavemap/memmap.py
wavemap/raw.py
wavemap/read.py
wavemap/write.py
wavemap/structure/__init__.py
wavemap/structure/structure.py
wavemap/structure/wave.py
wavemap-2.0.1.dist-info/LICENSE
wavemap-2.0.1.dist-info/METADATA
wavemap-2.0.1.dist-info/WHEEL
wavemap-2.0.1.dist-info/top_level.txt
wavemap-2.0.1.dist-info/RECORD
