Metadata-Version: 2.1
Name: wavemap
Version: 2.0.1
Summary: Memory map WAVE or raw audio files
Home-page: https://github.com/rec/wavemap
Author: Tom Ritchford
Author-email: tom@swirly.com
License: MIT
Keywords: testing,modules
Platform: UNKNOWN
Classifier: Development Status :: 4 - Beta
Classifier: Programming Language :: Python :: 3.6
Classifier: Programming Language :: Python :: 3.7
Classifier: Programming Language :: Python :: 3.8
Classifier: Programming Language :: Python :: 3.9
Classifier: Intended Audience :: Developers
Classifier: License :: OSI Approved :: MIT License
Classifier: Topic :: Software Development :: Libraries
Classifier: Topic :: Utilities
License-File: LICENSE
Requires-Dist: numpy
Requires-Dist: xmod
